ttsfm/__init__.py
ttsfm/async_client.py
ttsfm/audio.py
ttsfm/audio_processing.py
ttsfm/capabilities.py
ttsfm/cli.py
ttsfm/client.py
ttsfm/exceptions.py
ttsfm/models.py
ttsfm/utils.py
ttsfm-3.4.2.dist-info/licenses/LICENSE
ttsfm-3.4.2.dist-info/METADATA
ttsfm-3.4.2.dist-info/WHEEL
ttsfm-3.4.2.dist-info/entry_points.txt
ttsfm-3.4.2.dist-info/top_level.txt
ttsfm-3.4.2.dist-info/RECORD
