Metadata-Version: 2.4
Name: ttsfm
Version: 3.4.2
Summary: Text-to-Speech API Client with OpenAI compatibility
Author-email: dbcccc <120614547+dbccccccc@users.noreply.github.com>
Maintainer-email: dbcccc <120614547+dbccccccc@users.noreply.github.com>
License-Expression: MIT
Project-URL: Homepage, https://github.com/dbccccccc/ttsfm
Project-URL: Documentation, https://github.com/dbccccccc/ttsfm/blob/main/docs/
Project-URL: Repository, https://github.com/dbccccccc/ttsfm
Project-URL: Bug Tracker, https://github.com/dbccccccc/ttsfm/issues
Keywords: tts,text-to-speech,speech-synthesis,openai,api-client,audio,voice,speech
Classifier: Development Status :: 4 - Beta
Classifier: Intended Audience :: Developers
Classifier: Operating System :: OS Independent
Classifier: Programming Language :: Python :: 3
Classifier: Programming Language :: Python :: 3.8
Classifier: Programming Language :: Python :: 3.9
Classifier: Programming Language :: Python :: 3.10
Classifier: Programming Language :: Python :: 3.11
Classifier: Programming Language :: Python :: 3.12
Classifier: Topic :: Multimedia :: Sound/Audio :: Speech
Classifier: Topic :: Software Development :: Libraries :: Python Modules
Classifier: Topic :: Internet :: WWW/HTTP :: Dynamic Content
Requires-Python: >=3.8
License-File: LICENSE
Requires-Dist: requests>=2.25.0
Requires-Dist: aiohttp>=3.8.0
Requires-Dist: python-dotenv>=1.0.1
Provides-Extra: dev
Requires-Dist: pytest>=6.0; extra == "dev"
Requires-Dist: pytest-asyncio>=0.18.0; extra == "dev"
Requires-Dist: pytest-cov>=2.0; extra == "dev"
Requires-Dist: black>=22.0; extra == "dev"
Requires-Dist: isort>=5.0; extra == "dev"
Requires-Dist: flake8>=4.0; extra == "dev"
Requires-Dist: mypy>=0.900; extra == "dev"
Requires-Dist: pre-commit>=2.0; extra == "dev"
Provides-Extra: docs
Requires-Dist: sphinx>=4.0; extra == "docs"
Requires-Dist: sphinx-rtd-theme>=1.0; extra == "docs"
Requires-Dist: myst-parser>=0.17; extra == "docs"
Provides-Extra: web
Requires-Dist: flask>=2.0.0; extra == "web"
Requires-Dist: flask-cors>=3.0.10; extra == "web"
Requires-Dist: flask-socketio>=5.3.0; extra == "web"
Requires-Dist: python-socketio>=5.10.0; extra == "web"
Requires-Dist: eventlet>=0.33.3; extra == "web"
Requires-Dist: waitress>=3.0.0; extra == "web"
Requires-Dist: pydub>=0.25.0; extra == "web"
Requires-Dist: argon2-cffi>=23.1.0; extra == "web"
Dynamic: license-file
